xs1_api_client/__init__.py
xs1_api_client/api.py
xs1_api_client/api_constants.py
xs1_api_client/device/__init__.py
xs1_api_client/device/actuator/__init__.py
xs1_api_client/device/actuator/switch.py
xs1_api_client/device/actuator/thermostat.py
xs1_api_client/device/sensor/__init__.py
xs1_api_client-3.0.1.dist-info/LICENSE
xs1_api_client-3.0.1.dist-info/METADATA
xs1_api_client-3.0.1.dist-info/WHEEL
xs1_api_client-3.0.1.dist-info/top_level.txt
xs1_api_client-3.0.1.dist-info/RECORD
