Metadata-Version: 2.1
Name: xs1-api-client
Version: 3.0.1
Summary: A library to get and set values of the EZcontrol XS1 Gateway
Home-page: https://github.com/markusressel/xs1-api-client
Author: Markus Ressel
Author-email: mail@markusressel.de
License: GPLv3+
Platform: UNKNOWN
Classifier: Development Status :: 5 - Production/Stable
Classifier: License :: OSI Approved :: GNU General Public License v3 or later (GPLv3+)
Classifier: Programming Language :: Python :: 3
Classifier: Programming Language :: Python :: 3.5
Classifier: Programming Language :: Python :: 3.6
Classifier: Programming Language :: Python :: 3.7
Classifier: Programming Language :: Python :: 3.8
Requires-Dist: requests
Requires-Dist: urllib3
